cjm_fasthtml_tailwind/__init__.py
cjm_fasthtml_tailwind/_modidx.py
cjm_fasthtml_tailwind/builders/__init__.py
cjm_fasthtml_tailwind/builders/colors.py
cjm_fasthtml_tailwind/builders/scales.py
cjm_fasthtml_tailwind/cli/__init__.py
cjm_fasthtml_tailwind/cli/cli_config.py
cjm_fasthtml_tailwind/cli/core_utils_discovery.py
cjm_fasthtml_tailwind/cli/display.py
cjm_fasthtml_tailwind/cli/dynamic_examples.py
cjm_fasthtml_tailwind/cli/example_discovery.py
cjm_fasthtml_tailwind/cli/explorer.py
cjm_fasthtml_tailwind/cli/factory_extraction.py
cjm_fasthtml_tailwind/cli/helper_discovery.py
cjm_fasthtml_tailwind/cli/imports.py
cjm_fasthtml_tailwind/cli/pattern_scanner.py
cjm_fasthtml_tailwind/cli/search.py
cjm_fasthtml_tailwind/cli/test_code.py
cjm_fasthtml_tailwind/cli/utils.py
cjm_fasthtml_tailwind/core/__init__.py
cjm_fasthtml_tailwind/core/base.py
cjm_fasthtml_tailwind/core/resources.py
cjm_fasthtml_tailwind/core/testing.py
cjm_fasthtml_tailwind/utilities/__init__.py
cjm_fasthtml_tailwind/utilities/accessibility.py
cjm_fasthtml_tailwind/utilities/backgrounds.py
cjm_fasthtml_tailwind/utilities/borders.py
cjm_fasthtml_tailwind/utilities/effects.py
cjm_fasthtml_tailwind/utilities/filters.py
cjm_fasthtml_tailwind/utilities/flexbox_and_grid.py
cjm_fasthtml_tailwind/utilities/interactivity.py
cjm_fasthtml_tailwind/utilities/layout.py
cjm_fasthtml_tailwind/utilities/sizing.py
cjm_fasthtml_tailwind/utilities/spacing.py
cjm_fasthtml_tailwind/utilities/svg.py
cjm_fasthtml_tailwind/utilities/tables.py
cjm_fasthtml_tailwind/utilities/transforms.py
cjm_fasthtml_tailwind/utilities/transitions_and_animation.py
cjm_fasthtml_tailwind/utilities/typography.py
cjm_fasthtml_tailwind-0.0.42.dist-info/licenses/LICENSE
cjm_fasthtml_tailwind-0.0.42.dist-info/METADATA
cjm_fasthtml_tailwind-0.0.42.dist-info/WHEEL
cjm_fasthtml_tailwind-0.0.42.dist-info/entry_points.txt
cjm_fasthtml_tailwind-0.0.42.dist-info/top_level.txt
cjm_fasthtml_tailwind-0.0.42.dist-info/RECORD
